{"results": [{"id": 13089235, "name": "co ppm", "parameter": {"id": 8, "name": "co", "units": "ppm", "displayName": "CO"}, "datetimeFirst": {"utc": "2025-05-17T17:00:00Z", "local": "2025-05-17T11:00:00-06:00"}, "datetimeLast": {"utc": "2025-10-23T04:00:00Z", "local": "2025-10-22T22:00:00-06:00"}, "coverage": {"expectedCount": 1, "expectedInterval": "01:00:00", "observedCount": 3403, "observedInterval": "3403:00:00", "percentComplete": 340300.0, "percentCoverage": 340300.0, "datetimeFrom": {"utc": "2025-05-17T17:00:00Z", "local": "2025-05-17T11:00:00-06:00"}, "datetimeTo": {"utc": "2025-10-23T04:00:00Z", "local": "2025-10-22T22:00:00-06:00"}}, "latest": {"datetime": {"utc": "2025-10-23T04:00:00Z", "local": "2025-10-22T22:00:00-06:00"}, "value": 1.57, "coordinates": {"latitude": 25.784941666667, "longitude": -100.46339166667}}, "summary": {"min": 0.05, "q02": null, "q25": null, "median": null, "q75": null, "q98": null, "max": 3.31, "avg": 2.1568085106382977, "sd": null}}, {"id": 13089240, "name": "pm10 µg/m³", "parameter": {"id": 1, "name": "pm10", "units": "µg/m³", "displayName": "PM10"}, "datetimeFirst": {"utc": "2025-05-17T17:00:00Z", "local": "2025-05-17T11:00:00-06:00"}, "datetimeLast": {"utc": "2025-10-23T04:00:00Z", "local": "2025-10-22T22:00:00-06:00"}, "coverage": {"expectedCount": 1, "expectedInterval": "01:00:00", "observedCount": 3479, "observedInterval": "3479:00:00", "percentComplete": 347900.0, "percentCoverage": 347900.0, "datetimeFrom": {"utc": "2025-05-17T17:00:00Z", "local": "2025-05-17T11:00:00-06:00"}, "datetimeTo": {"utc": "2025-10-23T04:00:00Z", "local": "2025-10-22T22:00:00-06:00"}}, "latest": {"datetime": {"utc": "2025-10-23T04:00:00Z", "local": "2025-10-22T22:00:00-06:00"}, "value": 61.0, "coordinates": {"latitude": 25.784941666667, "longitude": -100.46339166667}}, "summary": {"min": 5.5, "q02": null, "q25": null, "median": null, "q75": null, "q98": null, "max": 564.0, "avg": 59.5531914893617, "sd": null}}, {"id": 13089241, "name": "o3 ppm", "parameter": {"id": 10, "name": "o3", "units": "ppm", "displayName": "O₃"}, "datetimeFirst": {"utc": "2025-05-17T17:00:00Z", "local": "2025-05-17T11:00:00-06:00"}, "datetimeLast": {"utc": "2025-10-23T04:00:00Z", "local": "2025-10-22T22:00:00-06:00"}, "coverage": {"expectedCount": 1, "expectedInterval": "01:00:00", "observedCount": 3500, "observedInterval": "3500:00:00", "percentComplete": 350000.0, "percentCoverage": 350000.0, "datetimeFrom": {"utc": "2025-05-17T17:00:00Z", "local": "2025-05-17T11:00:00-06:00"}, "datetimeTo": {"utc": "2025-10-23T04:00:00Z", "local": "2025-10-22T22:00:00-06:00"}}, "latest": {"datetime": {"utc": "2025-10-23T04:00:00Z", "local": "2025-10-22T22:00:00-06:00"}, "value": 0.015, "coordinates": {"latitude": 25.784941666667, "longitude": -100.46339166667}}, "summary": {"min": 0.002, "q02": null, "q25": null, "median": null, "q75": null, "q98": null, "max": 0.13, "avg": 0.03680851063829787, "sd": null}}, {"id": 13089243, "name": "so2 ppm", "parameter": {"id": 9, "name": "so2", "units": "ppm", "displayName": "SO₂"}, "datetimeFirst": {"utc": "2025-05-17T17:00:00Z", "local": "2025-05-17T11:00:00-06:00"}, "datetimeLast": {"utc": "2025-10-23T04:00:00Z", "local": "2025-10-22T22:00:00-06:00"}, "coverage": {"expectedCount": 1, "expectedInterval": "01:00:00", "observedCount": 3387, "observedInterval": "3387:00:00", "percentComplete": 338700.0, "percentCoverage": 338700.0, "datetimeFrom": {"utc": "2025-05-17T17:00:00Z", "local": "2025-05-17T11:00:00-06:00"}, "datetimeTo": {"utc": "2025-10-23T04:00:00Z", "local": "2025-10-22T22:00:00-06:00"}}, "latest": {"datetime": {"utc": "2025-10-23T04:00:00Z", "local": "2025-10-22T22:00:00-06:00"}, "value": 0.0035, "coordinates": {"latitude": 25.784941666667, "longitude": -100.46339166667}}, "summary": {"min": 0.0008, "q02": null, "q25": null, "median": null, "q75": null, "q98": null, "max": 0.0859, "avg": 0.004563829787234043, "sd": null}}, {"id": 13411741, "name": "no ppm", "parameter": {"id": 35, "name": "no", "units": "ppm", "displayName": "NO"}, "datetimeFirst": {"utc": "2025-06-23T22:00:00Z", "local": "2025-06-23T16:00:00-06:00"}, "datetimeLast": {"utc": "2025-10-23T04:00:00Z", "local": "2025-10-22T22:00:00-06:00"}, "coverage": {"expectedCount": 1, "expectedInterval": "01:00:00", "observedCount": 2565, "observedInterval": "2565:00:00", "percentComplete": 256500.0, "percentCoverage": 256500.0, "datetimeFrom": {"utc": "2025-06-23T22:00:00Z", "local": "2025-06-23T16:00:00-06:00"}, "datetimeTo": {"utc": "2025-10-23T04:00:00Z", "local": "2025-10-22T22:00:00-06:00"}}, "latest": {"datetime": {"utc": "2025-10-23T04:00:00Z", "local": "2025-10-22T22:00:00-06:00"}, "value": 0.0048, "coordinates": {"latitude": 25.784941666667, "longitude": -100.46339166667}}, "summary": {"min": 0.0009, "q02": null, "q25": null, "median": null, "q75": null, "q98": null, "max": 0.0999, "avg": 0.0024, "sd": null}}, {"id": 13411742, "name": "nox ppm", "parameter": {"id": 19840, "name": "nox", "units": "ppm", "displayName": "NOx"}, "datetimeFirst": {"utc": "2025-06-23T22:00:00Z", "local": "2025-06-23T16:00:00-06:00"}, "datetimeLast": {"utc": "2025-10-23T04:00:00Z", "local": "2025-10-22T22:00:00-06:00"}, "coverage": {"expectedCount": 1, "expectedInterval": "01:00:00", "observedCount": 2632, "observedInterval": "2632:00:00", "percentComplete": 263200.0, "percentCoverage": 263200.0, "datetimeFrom": {"utc": "2025-06-23T22:00:00Z", "local": "2025-06-23T16:00:00-06:00"}, "datetimeTo": {"utc": "2025-10-23T04:00:00Z", "local": "2025-10-22T22:00:00-06:00"}}, "latest": {"datetime": {"utc": "2025-10-23T04:00:00Z", "local": "2025-10-22T22:00:00-06:00"}, "value": 0.0286, "coordinates": {"latitude": 25.784941666667, "longitude": -100.46339166667}}, "summary": {"min": 0.0009, "q02": null, "q25": null, "median": null, "q75": null, "q98": null, "max": 0.1238, "avg": 0.006033333333333332, "sd": null}}, {"id": 13411743, "name": "no2 ppm", "parameter": {"id": 7, "name": "no2", "units": "ppm", "displayName": "NO₂"}, "datetimeFirst": {"utc": "2025-06-23T22:00:00Z", "local": "2025-06-23T16:00:00-06:00"}, "datetimeLast": {"utc": "2025-10-23T04:00:00Z", "local": "2025-10-22T22:00:00-06:00"}, "coverage": {"expectedCount": 1, "expectedInterval": "01:00:00", "observedCount": 2632, "observedInterval": "2632:00:00", "percentComplete": 263200.0, "percentCoverage": 263200.0, "datetimeFrom": {"utc": "2025-06-23T22:00:00Z", "local": "2025-06-23T16:00:00-06:00"}, "datetimeTo": {"utc": "2025-10-23T04:00:00Z", "local": "2025-10-22T22:00:00-06:00"}}, "latest": {"datetime": {"utc": "2025-10-23T04:00:00Z", "local": "2025-10-22T22:00:00-06:00"}, "value": 0.023899999999999998, "coordinates": {"latitude": 25.784941666667, "longitude": -100.46339166667}}, "summary": {"min": 0.0006, "q02": null, "q25": null, "median": null, "q75": null, "q98": null, "max": 0.0456, "avg": 0.003833333333333333, "sd": null}}, {"id": 13411744, "name": "pm25 µg/m³", "parameter": {"id": 2, "name": "pm25", "units": "µg/m³", "displayName": "PM2.5"}, "datetimeFirst": {"utc": "2025-06-24T00:00:00Z", "local": "2025-06-23T18:00:00-06:00"}, "datetimeLast": {"utc": "2025-10-21T09:00:00Z", "local": "2025-10-21T03:00:00-06:00"}, "coverage": {"expectedCount": 1, "expectedInterval": "01:00:00", "observedCount": 1177, "observedInterval": "1177:00:00", "percentComplete": 117700.0, "percentCoverage": 117700.0, "datetimeFrom": {"utc": "2025-06-24T00:00:00Z", "local": "2025-06-23T18:00:00-06:00"}, "datetimeTo": {"utc": "2025-10-21T09:00:00Z", "local": "2025-10-21T03:00:00-06:00"}}, "latest": {"datetime": {"utc": "2025-10-21T09:00:00Z", "local": "2025-10-21T03:00:00-06:00"}, "value": 10.19, "coordinates": {"latitude": 25.784941666667, "longitude": -100.46339166667}}, "summary": {"min": 2.45, "q02": null, "q25": null, "median": null, "q75": null, "q98": null, "max": 36.3, "avg": 10.52, "sd": null}}]}