{"results": [{"id": 1025, "name": "o3 ppm", "parameter": {"id": 10, "name": "o3", "units": "ppm", "displayName": "O₃"}, "datetimeFirst": {"utc": "2016-03-07T15:00:00Z", "local": "2016-03-07T09:00:00-06:00"}, "datetimeLast": {"utc": "2016-08-24T13:00:00Z", "local": "2016-08-24T08:00:00-05:00"}, "coverage": {"expectedCount": 1, "expectedInterval": "01:00:00", "observedCount": 883, "observedInterval": "883:00:00", "percentComplete": 88300.0, "percentCoverage": 88300.0, "datetimeFrom": {"utc": "2016-03-07T15:00:00Z", "local": "2016-03-07T09:00:00-06:00"}, "datetimeTo": {"utc": "2016-08-24T13:00:00Z", "local": "2016-08-24T08:00:00-05:00"}}, "latest": {"datetime": {"utc": "2016-08-24T13:00:00Z", "local": "2016-08-24T08:00:00-05:00"}, "value": 0.004, "coordinates": {"latitude": 25.745, "longitude": -100.25472}}, "summary": {"min": 0.0, "q02": null, "q25": null, "median": null, "q75": null, "q98": null, "max": 0.086, "avg": 0.02588674971687431, "sd": null}}, {"id": 1029, "name": "pm25 µg/m³", "parameter": {"id": 2, "name": "pm25", "units": "µg/m³", "displayName": "PM2.5"}, "datetimeFirst": {"utc": "2016-03-07T15:00:00Z", "local": "2016-03-07T09:00:00-06:00"}, "datetimeLast": {"utc": "2016-11-01T20:00:00Z", "local": "2016-11-01T14:00:00-06:00"}, "coverage": {"expectedCount": 1, "expectedInterval": "01:00:00", "observedCount": 908, "observedInterval": "908:00:00", "percentComplete": 90800.0, "percentCoverage": 90800.0, "datetimeFrom": {"utc": "2016-03-07T15:00:00Z", "local": "2016-03-07T09:00:00-06:00"}, "datetimeTo": {"utc": "2016-11-01T20:00:00Z", "local": "2016-11-01T14:00:00-06:00"}}, "latest": {"datetime": {"utc": "2016-11-01T20:00:00Z", "local": "2016-11-01T14:00:00-06:00"}, "value": 6.9, "coordinates": {"latitude": 25.745, "longitude": -100.25472}}, "summary": {"min": 0.0, "q02": null, "q25": null, "median": null, "q75": null, "q98": null, "max": 69.4, "avg": 1.9769823788546264, "sd": null}}, {"id": 1026, "name": "pm10 µg/m³", "parameter": {"id": 1, "name": "pm10", "units": "µg/m³", "displayName": "PM10"}, "datetimeFirst": {"utc": "2016-03-07T15:00:00Z", "local": "2016-03-07T09:00:00-06:00"}, "datetimeLast": {"utc": "2016-11-01T20:00:00Z", "local": "2016-11-01T14:00:00-06:00"}, "coverage": {"expectedCount": 1, "expectedInterval": "01:00:00", "observedCount": 871, "observedInterval": "871:00:00", "percentComplete": 87100.0, "percentCoverage": 87100.0, "datetimeFrom": {"utc": "2016-03-07T15:00:00Z", "local": "2016-03-07T09:00:00-06:00"}, "datetimeTo": {"utc": "2016-11-01T20:00:00Z", "local": "2016-11-01T14:00:00-06:00"}}, "latest": {"datetime": {"utc": "2016-11-01T20:00:00Z", "local": "2016-11-01T14:00:00-06:00"}, "value": 36.0, "coordinates": {"latitude": 25.745, "longitude": -100.25472}}, "summary": {"min": 0.0, "q02": null, "q25": null, "median": null, "q75": null, "q98": null, "max": 224.0, "avg": 65.42824339839265, "sd": null}}]}